glowmarkt/__init__.py
glowmarkt/glowmarkt.py
pyglowmarkt-0.2.data/scripts/glowmarkt-csv
pyglowmarkt-0.2.data/scripts/glowmarkt-dump
pyglowmarkt-0.2.dist-info/METADATA
pyglowmarkt-0.2.dist-info/WHEEL
pyglowmarkt-0.2.dist-info/top_level.txt
pyglowmarkt-0.2.dist-info/RECORD
