Metadata-Version: 2.1
Name: pyglowmarkt
Version: 0.2
Summary: Python API for accessing Hildebrand/Glowmarkt/Bright API to smart meter data
Home-page: https://github.com/cybermaggedon/pyglowmarkt
Author: Cybermaggedon
Author-email: mark@cyberapocalypse.co.uk
License: UNKNOWN
Download-URL: https://github.com/cybermaggedon/pyglowmarkt/archive/refs/tags/v0.1.tar.gz
Platform: UNKNOWN
Classifier: Programming Language :: Python :: 3
Classifier: License :: OSI Approved :: GNU General Public License v3 or later (GPLv3+)
Classifier: Operating System :: OS Independent
Requires-Python: >=3.6
Requires-Dist: requests
